whatsmynameLP2/whatsmyname2.py
whatsmynameLP2-1.0.0.dist-info/LICENSE
whatsmynameLP2-1.0.0.dist-info/METADATA
whatsmynameLP2-1.0.0.dist-info/WHEEL
whatsmynameLP2-1.0.0.dist-info/top_level.txt
whatsmynameLP2-1.0.0.dist-info/RECORD
