Metadata-Version: 2.1
Name: whatsmynameLP2
Version: 1.0.0
Summary: Say my name
Home-page: https://github.com/loupestana/repo1.git
Author: Lourenço Pestana
Author-email: luis.pestana@accenture.com
License: MIT
Platform: UNKNOWN
Classifier: Programming Language :: Python :: 3.7
Classifier: License :: OSI Approved :: MIT License
Classifier: Operating System :: OS Independent
